tabletoppy/__init__.py
tabletoppy/coin.py
tabletoppy/die.py
tabletoppy/randomisable.py
tabletoppy-0.2.1.dist-info/LICENSE
tabletoppy-0.2.1.dist-info/METADATA
tabletoppy-0.2.1.dist-info/WHEEL
tabletoppy-0.2.1.dist-info/RECORD
